ItunesLibrarian-1.0.4.data/data/README.md
ItunesLibrarian-1.0.4.dist-info/DESCRIPTION.rst
ItunesLibrarian-1.0.4.dist-info/METADATA
ItunesLibrarian-1.0.4.dist-info/RECORD
ItunesLibrarian-1.0.4.dist-info/WHEEL
ItunesLibrarian-1.0.4.dist-info/entry_points.txt
ItunesLibrarian-1.0.4.dist-info/metadata.json
ItunesLibrarian-1.0.4.dist-info/top_level.txt
ituneslibrarian/__init__.py
ituneslibrarian/__main__.py
ituneslibrarian/modify.py
ituneslibrarian/parse.py
ituneslibrarian/search.py
ituneslibrarian/utils.py
