Metadata-Version: 2.0
Name: ItunesLibrarian
Version: 1.0.4
Summary: UNKNOWN
Home-page: UNKNOWN
Author: Giacomo Rossetto
Author-email: jackyman_cs4@live.it
License: MIT
Platform: UNKNOWN
